MANIFEST.in
junkmodule.py
junkmodule_script.py
setup.cfg
setup.py
junkmodule.egg-info/PKG-INFO
junkmodule.egg-info/SOURCES.txt
junkmodule.egg-info/dependency_links.txt
junkmodule.egg-info/entry_points.txt
junkmodule.egg-info/requires.txt
junkmodule.egg-info/top_level.txt