Metadata-Version: 1.0
Name: junkmodule
Version: 2017.1.16.1427
Summary: junk testing module
Home-page: https://github.com/wdbm/junkmodule
Author: Will Breaden Madden
Author-email: wbm@protonmail.ch
License: GPLv3
Platform: UNKNOWN
